hexapixl/__init__.py
hexapixl/main.py
hexapixl-1.1.1.dist-info/LICENSE
hexapixl-1.1.1.dist-info/METADATA
hexapixl-1.1.1.dist-info/WHEEL
hexapixl-1.1.1.dist-info/entry_points.txt
hexapixl-1.1.1.dist-info/top_level.txt
hexapixl-1.1.1.dist-info/RECORD
