Metadata-Version: 2.1
Name: hexapixl
Version: 1.1.1
Summary: png <-> hex
Author: werzq
Classifier: Intended Audience :: Developers
Classifier: License :: OSI Approved :: MIT License
Classifier: Programming Language :: Python :: 3
License-File: LICENSE
